CHANGES.txt
LICENSE
MANIFEST.in
README.rst
requirements.txt
setup.py
magma/__init__.py
magma/base.py
magma/courses.py
magma/session.py
magma/souputils.py
p7magma.egg-info/PKG-INFO
p7magma.egg-info/SOURCES.txt
p7magma.egg-info/dependency_links.txt
p7magma.egg-info/requires.txt
p7magma.egg-info/top_level.txt