Metadata-Version: 1.1
Name: p7magma
Version: 0.1.2
Summary: Magma Python interface
Home-page: https://github.com/bfontaine/p7magma
Author: Baptiste Fontaine
Author-email: b@ptistefontaine.fr
License: Copyright © 2015 – Baptiste Fontaine
